pydantic_translations/__init__.py
pydantic_translations/_constants.py
pydantic_translations/_messages.py
pydantic_translations/_translator.py
pydantic_translations/py.typed
pydantic_translations/locales/de.mo
pydantic_translations/locales/en.mo
pydantic_translations/locales/es.mo
pydantic_translations/locales/fr.mo
pydantic_translations/locales/it.mo
pydantic_translations/locales/nl.mo
pydantic_translations/locales/ru.mo
pydantic_translations/locales/zh_cn.mo
pydantic_translations-0.4.1.dist-info/LICENSE
pydantic_translations-0.4.1.dist-info/WHEEL
pydantic_translations-0.4.1.dist-info/METADATA
pydantic_translations-0.4.1.dist-info/RECORD
