Metadata-Version: 2.1
Name: pydantic-translations
Version: 0.4.1
Summary: Translations for pydantic errors.
Keywords: mypy,typing,annotations,type annotations
Author-email: Gram <git@orsinium.dev>
Requires-Python: >=3.9
Classifier: Development Status :: 5 - Production/Stable
Classifier: Intended Audience :: Developers
Classifier: License :: OSI Approved :: MIT License
Classifier: Programming Language :: Python
Classifier: Typing :: Typed
Requires-Dist: l10n
Requires-Dist: pydantic >=1.0.0,<2.0.0
Requires-Dist: l10n[cli] ; extra == "l10n"
Requires-Dist: mypy ; extra == "l10n"
Requires-Dist: flake8 ; extra == "lint"
Requires-Dist: isort ; extra == "lint"
Requires-Dist: mypy ; extra == "lint"
Requires-Dist: pytest ; extra == "test"
Requires-Dist: pytest-cov ; extra == "test"
Project-URL: Source, https://github.com/orsinium-labs/pydantic-translations
Provides-Extra: l10n
Provides-Extra: lint
Provides-Extra: test
